[
  {
    "ContainingType": "Geek_API.Controllers.v1.UserController",
    "Method": "GetUsersAsync",
    "RelativePath": "api/v1/User",
    "HttpMethod": "GET",
    "IsController": true,
    "Order": 0,
    "Parameters": [
      {
        "Name": "page",
        "Type": "System.Int32",
        "IsRequired": false
      },
      {
        "Name": "pageSize",
        "Type": "System.Int32",
        "IsRequired": false
      }
    ],
    "ReturnTypes": []
  },
  {
    "ContainingType": "Geek_API.Controllers.v1.UserController",
    "Method": "AddUserAsync",
    "RelativePath": "api/v1/User",
    "HttpMethod": "POST",
    "IsController": true,
    "Order": 0,
    "Parameters": [
      {
        "Name": "user",
        "Type": "Core.Models.UserUpdateRequest",
        "IsRequired": true
      }
    ],
    "ReturnTypes": []
  },
  {
    "ContainingType": "Geek_API.Controllers.v1.UserController",
    "Method": "GetUserAsync",
    "RelativePath": "api/v1/User/{id}",
    "HttpMethod": "GET",
    "IsController": true,
    "Order": 0,
    "Parameters": [
      {
        "Name": "id",
        "Type": "System.Int32",
        "IsRequired": true
      }
    ],
    "ReturnTypes": []
  },
  {
    "ContainingType": "Geek_API.Controllers.v1.UserController",
    "Method": "DeleteUserAsync",
    "RelativePath": "api/v1/User/{id}",
    "HttpMethod": "DELETE",
    "IsController": true,
    "Order": 0,
    "Parameters": [
      {
        "Name": "id",
        "Type": "System.Int32",
        "IsRequired": true
      }
    ],
    "ReturnTypes": []
  },
  {
    "ContainingType": "Geek_API.Controllers.v1.UserController",
    "Method": "UpdateUser",
    "RelativePath": "api/v1/User/{id}",
    "HttpMethod": "PUT",
    "IsController": true,
    "Order": 0,
    "Parameters": [
      {
        "Name": "user",
        "Type": "Core.Models.UserUpdateRequest",
        "IsRequired": true
      },
      {
        "Name": "id",
        "Type": "System.Int32",
        "IsRequired": true
      }
    ],
    "ReturnTypes": []
  },
  {
    "ContainingType": "Geek_API.Controllers.v1.UserController",
    "Method": "AddUserAsync",
    "RelativePath": "api/v1/User/byCommunity",
    "HttpMethod": "GET",
    "IsController": true,
    "Order": 0,
    "Parameters": [
      {
        "Name": "user",
        "Type": "Core.Models.UserUpdateRequest",
        "IsRequired": true
      }
    ],
    "ReturnTypes": []
  }
]